test/__init__.py
test/test_alert.py
test/test_alert_info.py
test/test_alert_info_area.py
test/test_alert_info_area_geocode.py
test/test_alert_info_event_code.py
test/test_alert_info_parameter.py
test/test_alert_info_resource.py
test/test_cap_api.py
test/test_cause.py
test/test_code_page_data_item.py
test/test_county.py
test/test_decoder_fallback.py
test/test_encoder_fallback.py
test/test_encoding.py
test/test_formatted_content_result_alert.py
test/test_formatted_content_result_list_alert.py
test/test_i_required_member_selector.py
test/test_media_type_formatter.py
test/test_media_type_header_value.py
test/test_media_type_mapping.py
test/test_micro_blog_post.py
test/test_municipality.py
test/test_name_value_header_value.py
test/test_region_api.py
test/test_station.py
test/test_warning.py
test/test_warning_api.py
varsom_landslide_client/__init__.py
varsom_landslide_client/api_client.py
varsom_landslide_client/configuration.py
varsom_landslide_client/rest.py
varsom_landslide_client/api/__init__.py
varsom_landslide_client/api/cap_api.py
varsom_landslide_client/api/region_api.py
varsom_landslide_client/api/warning_api.py
varsom_landslide_client/models/__init__.py
varsom_landslide_client/models/alert.py
varsom_landslide_client/models/alert_info.py
varsom_landslide_client/models/alert_info_area.py
varsom_landslide_client/models/alert_info_area_geocode.py
varsom_landslide_client/models/alert_info_event_code.py
varsom_landslide_client/models/alert_info_parameter.py
varsom_landslide_client/models/alert_info_resource.py
varsom_landslide_client/models/cause.py
varsom_landslide_client/models/code_page_data_item.py
varsom_landslide_client/models/county.py
varsom_landslide_client/models/decoder_fallback.py
varsom_landslide_client/models/encoder_fallback.py
varsom_landslide_client/models/encoding.py
varsom_landslide_client/models/formatted_content_result_alert.py
varsom_landslide_client/models/formatted_content_result_list_alert.py
varsom_landslide_client-1.0.0.dist-info/LICENSE
varsom_landslide_client-1.0.0.dist-info/METADATA
varsom_landslide_client-1.0.0.dist-info/WHEEL
varsom_landslide_client-1.0.0.dist-info/top_level.txt
varsom_landslide_client-1.0.0.dist-info/RECORD
