Metadata-Version: 2.1
Name: varsom-landslide-client
Version: 1.0.0
Summary: Jordskredvarsel API
Home-page: https://github.com/NVE/python-varsom-landslide-client
Author-email: regobs@nve.no
License: UNKNOWN
Keywords: Swagger,Jordskredvarsel API
Platform: UNKNOWN
Requires-Python: >=3.4
Requires-Dist: urllib3 (>=1.15)
Requires-Dist: six (>=1.10)
Requires-Dist: certifi
Requires-Dist: python-dateutil
